rdreturnnotice/EcsInterface.py
rdreturnnotice/__init__.py
rdreturnnotice/mainModel.py
rdreturnnotice/metadata.py
rdreturnnotice/operation.py
rdreturnnotice/utility.py
rdreturnsales/EcsInterface.py
rdreturnsales/__init__.py
rdreturnsales/mainModel.py
rdreturnsales/metadata.py
rdreturnsales/operation.py
rdreturnsales/utility.py
rdreturnnotice-1.2.3.dist-info/METADATA
rdreturnnotice-1.2.3.dist-info/NoticeOfReturn.py
rdreturnnotice-1.2.3.dist-info/WHEEL
rdreturnnotice-1.2.3.dist-info/top_level.txt
rdreturnnotice-1.2.3.dist-info/RECORD
